LICENSE.txt
MANIFEST.in
README.md
requirements.txt
setup.py
WebRequest/ChromiumMixin.py
WebRequest/Domain_Constants.py
WebRequest/Exceptions.py
WebRequest/Handlers.py
WebRequest/HeaderParseMonkeyPatch.py
WebRequest/Test.py
WebRequest/UA_Constants.py
WebRequest/WebRequestClass.py
WebRequest/__init__.py
WebRequest/iri2uri.py
WebRequest/utility.py
WebRequest.egg-info/PKG-INFO
WebRequest.egg-info/SOURCES.txt
WebRequest.egg-info/dependency_links.txt
WebRequest.egg-info/requires.txt
WebRequest.egg-info/top_level.txt
WebRequest/Captcha/AntiCaptchaSolver.py
WebRequest/Captcha/CaptchaSolverBase.py
WebRequest/Captcha/PunchPort.py
WebRequest/Captcha/SocksProxy.py
WebRequest/Captcha/TwoCaptchaSolver.py
WebRequest/Captcha/__init__.py
WebRequest/Captcha/socks5.py