Metadata-Version: 2.1
Name: WebRequest
Version: 0.1.0
Summary: Like `requests`, but shittier.
Home-page: https://github.com/fake-name/WebRequest
Author: Connor Wolf
Author-email: github@imaginaryindustries.com
Classifier: Programming Language :: Python :: 3
Classifier: Development Status :: 4 - Beta
Classifier: Intended Audience :: Developers
Classifier: Operating System :: POSIX :: Linux
License-File: LICENSE.txt
Requires-Dist: ChromeController>=0.3.19
Requires-Dist: beautifulsoup4>=4.6.0
Requires-Dist: faust-cchardet
Requires-Dist: lxml>=4.1.1
Requires-Dist: PySocks>=1.6.8
Requires-Dist: upnpclient==1.0.3
Requires-Dist: python_anticaptcha==1.0.0
Requires-Dist: pycryptodome
